odoo/addons/mrp_bom_structure_report_level_1/README.rst
odoo/addons/mrp_bom_structure_report_level_1/__init__.py
odoo/addons/mrp_bom_structure_report_level_1/__manifest__.py
odoo/addons/mrp_bom_structure_report_level_1/i18n/de.po
odoo/addons/mrp_bom_structure_report_level_1/i18n/fr.po
odoo/addons/mrp_bom_structure_report_level_1/i18n/it.po
odoo/addons/mrp_bom_structure_report_level_1/i18n/mrp_bom_structure_report_level_1.pot
odoo/addons/mrp_bom_structure_report_level_1/readme/CONTRIBUTORS.md
odoo/addons/mrp_bom_structure_report_level_1/readme/DESCRIPTION.md
odoo/addons/mrp_bom_structure_report_level_1/readme/USAGE.md
odoo/addons/mrp_bom_structure_report_level_1/report/__init__.py
odoo/addons/mrp_bom_structure_report_level_1/report/mrp_report_bom_structure_level_1.py
odoo/addons/mrp_bom_structure_report_level_1/report/mrp_report_bom_structure_level_1.xml
odoo/addons/mrp_bom_structure_report_level_1/static/description/icon.png
odoo/addons/mrp_bom_structure_report_level_1/static/description/index.html
odoo/addons/mrp_bom_structure_report_level_1/views/mrp_bom_view.xml
odoo_addon_mrp_bom_structure_report_level_1-17.0.1.0.0.2.dist-info/METADATA
odoo_addon_mrp_bom_structure_report_level_1-17.0.1.0.0.2.dist-info/WHEEL
odoo_addon_mrp_bom_structure_report_level_1-17.0.1.0.0.2.dist-info/top_level.txt
odoo_addon_mrp_bom_structure_report_level_1-17.0.1.0.0.2.dist-info/RECORD
